{
    "28756": {
        "name": "Phú Khương",
        "type": "phuong",
        "slug": "phu-khuong",
        "name_with_type": "Phường Phú Khương",
        "path": "Phú Khương, Bến Tre, Bến Tre",
        "path_with_type": "Phường Phú Khương, Thành phố Bến Tre, Tỉnh Bến Tre",
        "code": "28756",
        "parent_code": "829"
    },
    "28757": {
        "name": "Phú Tân",
        "type": "phuong",
        "slug": "phu-tan",
        "name_with_type": "Phường Phú Tân",
        "path": "Phú Tân, Bến Tre, Bến Tre",
        "path_with_type": "Phường Phú Tân, Thành phố Bến Tre, Tỉnh Bến Tre",
        "code": "28757",
        "parent_code": "829"
    },
    "28759": {
        "name": "8",
        "type": "phuong",
        "slug": "8",
        "name_with_type": "Phường 8",
        "path": "8, Bến Tre, Bến Tre",
        "path_with_type": "Phường 8, Thành phố Bến Tre, Tỉnh Bến Tre",
        "code": "28759",
        "parent_code": "829"
    },
    "28762": {
        "name": "6",
        "type": "phuong",
        "slug": "6",
        "name_with_type": "Phường 6",
        "path": "6, Bến Tre, Bến Tre",
        "path_with_type": "Phường 6, Thành phố Bến Tre, Tỉnh Bến Tre",
        "code": "28762",
        "parent_code": "829"
    },
    "28765": {
        "name": "4",
        "type": "phuong",
        "slug": "4",
        "name_with_type": "Phường 4",
        "path": "4, Bến Tre, Bến Tre",
        "path_with_type": "Phường 4, Thành phố Bến Tre, Tỉnh Bến Tre",
        "code": "28765",
        "parent_code": "829"
    },
    "28768": {
        "name": "5",
        "type": "phuong",
        "slug": "5",
        "name_with_type": "Phường 5",
        "path": "5, Bến Tre, Bến Tre",
        "path_with_type": "Phường 5, Thành phố Bến Tre, Tỉnh Bến Tre",
        "code": "28768",
        "parent_code": "829"
    },
    "28777": {
        "name": "An Hội",
        "type": "phuong",
        "slug": "an-hoi",
        "name_with_type": "Phường An Hội",
        "path": "An Hội, Bến Tre, Bến Tre",
        "path_with_type": "Phường An Hội, Thành phố Bến Tre, Tỉnh Bến Tre",
        "code": "28777",
        "parent_code": "829"
    },
    "28780": {
        "name": "7",
        "type": "phuong",
        "slug": "7",
        "name_with_type": "Phường 7",
        "path": "7, Bến Tre, Bến Tre",
        "path_with_type": "Phường 7, Thành phố Bến Tre, Tỉnh Bến Tre",
        "code": "28780",
        "parent_code": "829"
    },
    "28783": {
        "name": "Sơn Đông",
        "type": "xa",
        "slug": "son-dong",
        "name_with_type": "Xã Sơn Đông",
        "path": "Sơn Đông, Bến Tre, Bến Tre",
        "path_with_type": "Xã Sơn Đông, Thành phố Bến Tre, Tỉnh Bến Tre",
        "code": "28783",
        "parent_code": "829"
    },
    "28786": {
        "name": "Phú Hưng",
        "type": "xa",
        "slug": "phu-hung",
        "name_with_type": "Xã Phú Hưng",
        "path": "Phú Hưng, Bến Tre, Bến Tre",
        "path_with_type": "Xã Phú Hưng, Thành phố Bến Tre, Tỉnh Bến Tre",
        "code": "28786",
        "parent_code": "829"
    },
    "28789": {
        "name": "Bình Phú",
        "type": "xa",
        "slug": "binh-phu",
        "name_with_type": "Xã Bình Phú",
        "path": "Bình Phú, Bến Tre, Bến Tre",
        "path_with_type": "Xã Bình Phú, Thành phố Bến Tre, Tỉnh Bến Tre",
        "code": "28789",
        "parent_code": "829"
    },
    "28792": {
        "name": "Mỹ Thạnh An",
        "type": "xa",
        "slug": "my-thanh-an",
        "name_with_type": "Xã Mỹ Thạnh An",
        "path": "Mỹ Thạnh An, Bến Tre, Bến Tre",
        "path_with_type": "Xã Mỹ Thạnh An, Thành phố Bến Tre, Tỉnh Bến Tre",
        "code": "28792",
        "parent_code": "829"
    },
    "28795": {
        "name": "Nhơn Thạnh",
        "type": "xa",
        "slug": "nhon-thanh",
        "name_with_type": "Xã Nhơn Thạnh",
        "path": "Nhơn Thạnh, Bến Tre, Bến Tre",
        "path_with_type": "Xã Nhơn Thạnh, Thành phố Bến Tre, Tỉnh Bến Tre",
        "code": "28795",
        "parent_code": "829"
    },
    "28798": {
        "name": "Phú Nhuận",
        "type": "xa",
        "slug": "phu-nhuan",
        "name_with_type": "Xã Phú Nhuận",
        "path": "Phú Nhuận, Bến Tre, Bến Tre",
        "path_with_type": "Xã Phú Nhuận, Thành phố Bến Tre, Tỉnh Bến Tre",
        "code": "28798",
        "parent_code": "829"
    }
}